trayapp/__init__.py
trayapp/tray_app.py
trayapp/tray_menu.py
trayapp/items/__init__.py
trayapp/items/radiobutton.py
trayapp/items/submenu.py
trayapp-0.1.4.dist-info/LICENSE
trayapp-0.1.4.dist-info/METADATA
trayapp-0.1.4.dist-info/WHEEL
trayapp-0.1.4.dist-info/top_level.txt
trayapp-0.1.4.dist-info/RECORD
