Metadata-Version: 2.1
Name: trayapp
Version: 0.1.4
Summary: Library for creating system tray applications, based on Moses Palmér's 'pystray' library
Home-page: https://github.com/RoW171/trayPy
Author: Robin 'r0w' Weiland
Author-email: robin.weiland@gmx.de
License: MIT
Keywords: systemtray,tray,app
Platform: UNKNOWN
Classifier: Development Status :: 5 - Production/Stable
Classifier: Intended Audience :: Developers
Classifier: Topic :: Software Development
Classifier: License :: OSI Approved :: MIT License
Classifier: Programming Language :: Python :: 3.8
Classifier: Operating System :: OS Independent
Requires: pystray
Requires: PIL
Requires-Python: >=3.8
